echo_env/__init__.py
echo_env/accessors.py
echo_env/wrappers.py
echo_env-0.1.3.dist-info/METADATA
echo_env-0.1.3.dist-info/WHEEL
echo_env-0.1.3.dist-info/top_level.txt
echo_env-0.1.3.dist-info/RECORD
